NiukeJinrongXingyeMingqiBiMianshiXiaozhaoQiuzhiGonglve20212022Fix1/README.md
NiukeJinrongXingyeMingqiBiMianshiXiaozhaoQiuzhiGonglve20212022Fix1/__init__.py
NiukeJinrongXingyeMingqiBiMianshiXiaozhaoQiuzhiGonglve20212022Fix1/__main__.py
NiukeJinrongXingyeMingqiBiMianshiXiaozhaoQiuzhiGonglve20212022Fix1/file.epub
NiukeJinrongXingyeMingqiBiMianshiXiaozhaoQiuzhiGonglve20212022Fix1/index.html
NiukeJinrongXingyeMingqiBiMianshiXiaozhaoQiuzhiGonglve20212022Fix1/css/__init__.py
NiukeJinrongXingyeMingqiBiMianshiXiaozhaoQiuzhiGonglve20212022Fix1/css/annotations.css
NiukeJinrongXingyeMingqiBiMianshiXiaozhaoQiuzhiGonglve20212022Fix1/css/main.css
NiukeJinrongXingyeMingqiBiMianshiXiaozhaoQiuzhiGonglve20212022Fix1/css/normalize.css
NiukeJinrongXingyeMingqiBiMianshiXiaozhaoQiuzhiGonglve20212022Fix1/css/popup.css
NiukeJinrongXingyeMingqiBiMianshiXiaozhaoQiuzhiGonglve20212022Fix1/font/__init__.py
NiukeJinrongXingyeMingqiBiMianshiXiaozhaoQiuzhiGonglve20212022Fix1/font/fontello.eot
NiukeJinrongXingyeMingqiBiMianshiXiaozhaoQiuzhiGonglve20212022Fix1/font/fontello.svg
NiukeJinrongXingyeMingqiBiMianshiXiaozhaoQiuzhiGonglve20212022Fix1/font/fontello.ttf
NiukeJinrongXingyeMingqiBiMianshiXiaozhaoQiuzhiGonglve20212022Fix1/font/fontello.woff
NiukeJinrongXingyeMingqiBiMianshiXiaozhaoQiuzhiGonglve20212022Fix1/img/__init__.py
NiukeJinrongXingyeMingqiBiMianshiXiaozhaoQiuzhiGonglve20212022Fix1/img/annotator-glyph-sprite.png
NiukeJinrongXingyeMingqiBiMianshiXiaozhaoQiuzhiGonglve20212022Fix1/img/annotator-icon-sprite.png
NiukeJinrongXingyeMingqiBiMianshiXiaozhaoQiuzhiGonglve20212022Fix1/img/apple-touch-icon.png
NiukeJinrongXingyeMingqiBiMianshiXiaozhaoQiuzhiGonglve20212022Fix1/img/cancelfullscreen.png
NiukeJinrongXingyeMingqiBiMianshiXiaozhaoQiuzhiGonglve20212022Fix1/img/close.png
NiukeJinrongXingyeMingqiBiMianshiXiaozhaoQiuzhiGonglve20212022Fix1/img/fullscreen.png
NiukeJinrongXingyeMingqiBiMianshiXiaozhaoQiuzhiGonglve20212022Fix1/img/loader.gif
niuke_jinrong_xingye_mingqi_bi_mianshi_xiaozhao_qiuzhi_gonglve_2021_2022_fix1-2025.3.25.0.dist-info/METADATA
niuke_jinrong_xingye_mingqi_bi_mianshi_xiaozhao_qiuzhi_gonglve_2021_2022_fix1-2025.3.25.0.dist-info/WHEEL
niuke_jinrong_xingye_mingqi_bi_mianshi_xiaozhao_qiuzhi_gonglve_2021_2022_fix1-2025.3.25.0.dist-info/entry_points.txt
niuke_jinrong_xingye_mingqi_bi_mianshi_xiaozhao_qiuzhi_gonglve_2021_2022_fix1-2025.3.25.0.dist-info/top_level.txt
niuke_jinrong_xingye_mingqi_bi_mianshi_xiaozhao_qiuzhi_gonglve_2021_2022_fix1-2025.3.25.0.dist-info/RECORD
